{
  "building_id": "brick-template-catalog-restructure-0-p9-dogfood-0601",
  "declared_plan_copy": {
    "building_id": "brick-template-catalog-restructure-0-p9-dogfood-0601",
    "chain_preset_ref": "building-chain-preset:brick-protocol-engine-feature-hard",
    "composition_mode": "coo-declared-dogfood-plan",
    "declared_by": "coo",
    "not_proven": [
      "semantic fitness of physical Brick templates",
      "provider behavior or provider reliability",
      "P10 old registry deletion safety"
    ],
    "owner_axis": "Brick",
    "plan_ref": "building-plan:brick-template-catalog-restructure-0-p9-dogfood",
    "plan_shape": "linear",
    "proof_limits": [
      "support evidence only",
      "P9 dogfood validates split catalog declaration evidence binding only",
      "not source truth",
      "not success judgment",
      "not quality judgment",
      "not Movement authority"
    ],
    "selected_adapter_ref": "adapter:local",
    "selected_model_ref": "model:default",
    "selected_shape_ref": "building-shape:design-needed",
    "step_template_expansion": {
      "expanded_brick_template_refs": [
        "brick/templates/design/standard-design-return.yaml",
        "brick/templates/do/standard-work-return.yaml",
        "brick/templates/review/standard-code-attack-qa-return.yaml",
        "brick/templates/review/standard-transition-concern-return.yaml",
        "brick/templates/review/standard-axis-attack-qa-return.yaml",
        "brick/templates/review/standard-evidence-integrity-return.yaml",
        "brick/templates/closure/standard-closure-with-parent-delta.yaml"
      ],
      "expanded_step_template_refs": [
        "building-step-template:design",
        "building-step-template:work",
        "building-step-template:code-attack-qa",
        "building-step-template:axis-attack-qa",
        "building-step-template:evidence-integrity",
        "building-step-template:closure"
      ],
      "expansion_rule": "step templates expand only after caller / COO selected chain, shape, and target refs",
      "not_proven": [
        "semantic fitness of selected chain preset or step template",
        "future Building run correctness",
        "future Agent or provider quality"
      ],
      "proof_limits": [
        "step template expansion support rendering only",
        "not automatic shape selection",
        "not target inference",
        "not Movement choice",
        "not source truth",
        "not success judgment",
        "not quality judgment",
        "not Movement authority"
      ],
      "registry_ref": "brick-template-catalog:split-p3b-p4",
      "selection_rule": "caller_or_coo_declared_only"
    },
    "steps": [
      {
        "rows": [
          {
            "axis": "Brick",
            "brick_instance_ref": "brick-btcr0-p9-01-design",
            "brick_work_ref": "work:btcr0-p9-01-design",
            "comparison_rule": "Observe only that required returned fields are present; do not judge success, quality, source truth, or Movement.",
            "required_return_shape": "returned_summary, evidence_refs",
            "row_ref": "brick-row:btcr0-p9-01-design",
            "source_facts": [
              "brick/templates/shapes/catalog.yaml",
              "brick/templates/shapes/step-templates.yaml",
              "brick/templates/shapes/chain-presets-brick-protocol.yaml",
              "project/brick-protocol/status/kernel/brick-template-catalog-restructure-0-p8-checker-fire-closure-0601.md"
            ],
            "work_statement": "P9 dogfood observation for design: return local support evidence that this step walked through the split Brick template catalog path."
          },
          {
            "agent_object_ref": "agent-object:design-lead",
            "axis": "Agent",
            "row_ref": "btcr0-p9-01-design:agent"
          },
          {
            "axis": "Link",
            "declared_gate_refs": [
              "link-gate:default-transition",
              "link-gate:strict"
            ],
            "movement": "forward",
            "next_brick_instance_ref": "brick-btcr0-p9-work",
            "row_ref": "btcr0-p9-01-design:link",
            "target_ref": "brick-btcr0-p9-work"
          }
        ],
        "step_ref": "btcr0-p9-01-design",
        "step_template_ref": "building-step-template:design"
      },
      {
        "rows": [
          {
            "axis": "Brick",
            "brick_instance_ref": "brick-btcr0-p9-02-work",
            "brick_work_ref": "work:btcr0-p9-02-work",
            "comparison_rule": "Observe only that required returned fields are present; do not judge success, quality, source truth, or Movement.",
            "required_return_shape": "returned_summary, evidence_refs",
            "row_ref": "brick-row:btcr0-p9-02-work",
            "source_facts": [
              "brick/templates/shapes/catalog.yaml",
              "brick/templates/shapes/step-templates.yaml",
              "brick/templates/shapes/chain-presets-brick-protocol.yaml",
              "project/brick-protocol/status/kernel/brick-template-catalog-restructure-0-p8-checker-fire-closure-0601.md"
            ],
            "work_statement": "P9 dogfood observation for work: return local support evidence that this step walked through the split Brick template catalog path."
          },
          {
            "agent_object_ref": "agent-object:dev",
            "axis": "Agent",
            "row_ref": "btcr0-p9-02-work:agent"
          },
          {
            "axis": "Link",
            "declared_gate_refs": [
              "link-gate:default-transition",
              "link-gate:strict"
            ],
            "movement": "forward",
            "next_brick_instance_ref": "brick-btcr0-p9-code-attack-qa",
            "row_ref": "btcr0-p9-02-work:link",
            "target_ref": "brick-btcr0-p9-code-attack-qa"
          }
        ],
        "step_ref": "btcr0-p9-02-work",
        "step_template_ref": "building-step-template:work"
      },
      {
        "rows": [
          {
            "axis": "Brick",
            "brick_instance_ref": "brick-btcr0-p9-03-code-attack-qa",
            "brick_work_ref": "work:btcr0-p9-03-code-attack-qa",
            "comparison_rule": "Observe only that required returned fields are present; do not judge success, quality, source truth, or Movement.",
            "required_return_shape": "returned_summary, evidence_refs",
            "row_ref": "brick-row:btcr0-p9-03-code-attack-qa",
            "source_facts": [
              "brick/templates/shapes/catalog.yaml",
              "brick/templates/shapes/step-templates.yaml",
              "brick/templates/shapes/chain-presets-brick-protocol.yaml",
              "project/brick-protocol/status/kernel/brick-template-catalog-restructure-0-p8-checker-fire-closure-0601.md"
            ],
            "work_statement": "P9 dogfood observation for code-attack-qa: return local support evidence that this step walked through the split Brick template catalog path."
          },
          {
            "agent_object_ref": "agent-object:qa",
            "axis": "Agent",
            "row_ref": "btcr0-p9-03-code-attack-qa:agent"
          },
          {
            "axis": "Link",
            "declared_gate_refs": [
              "link-gate:default-transition",
              "link-gate:strict"
            ],
            "movement": "forward",
            "next_brick_instance_ref": "brick-btcr0-p9-axis-attack-qa",
            "row_ref": "btcr0-p9-03-code-attack-qa:link",
            "target_ref": "brick-btcr0-p9-axis-attack-qa"
          }
        ],
        "step_ref": "btcr0-p9-03-code-attack-qa",
        "step_template_ref": "building-step-template:code-attack-qa"
      },
      {
        "rows": [
          {
            "axis": "Brick",
            "brick_instance_ref": "brick-btcr0-p9-04-axis-attack-qa",
            "brick_work_ref": "work:btcr0-p9-04-axis-attack-qa",
            "comparison_rule": "Observe only that required returned fields are present; do not judge success, quality, source truth, or Movement.",
            "required_return_shape": "returned_summary, evidence_refs",
            "row_ref": "brick-row:btcr0-p9-04-axis-attack-qa",
            "source_facts": [
              "brick/templates/shapes/catalog.yaml",
              "brick/templates/shapes/step-templates.yaml",
              "brick/templates/shapes/chain-presets-brick-protocol.yaml",
              "project/brick-protocol/status/kernel/brick-template-catalog-restructure-0-p8-checker-fire-closure-0601.md"
            ],
            "work_statement": "P9 dogfood observation for axis-attack-qa: return local support evidence that this step walked through the split Brick template catalog path."
          },
          {
            "agent_object_ref": "agent-object:inspector",
            "axis": "Agent",
            "row_ref": "btcr0-p9-04-axis-attack-qa:agent"
          },
          {
            "axis": "Link",
            "declared_gate_refs": [
              "link-gate:default-transition",
              "link-gate:strict"
            ],
            "movement": "forward",
            "next_brick_instance_ref": "brick-btcr0-p9-evidence-integrity",
            "row_ref": "btcr0-p9-04-axis-attack-qa:link",
            "target_ref": "brick-btcr0-p9-evidence-integrity"
          }
        ],
        "step_ref": "btcr0-p9-04-axis-attack-qa",
        "step_template_ref": "building-step-template:axis-attack-qa"
      },
      {
        "rows": [
          {
            "axis": "Brick",
            "brick_instance_ref": "brick-btcr0-p9-05-evidence-integrity",
            "brick_work_ref": "work:btcr0-p9-05-evidence-integrity",
            "comparison_rule": "Observe only that required returned fields are present; do not judge success, quality, source truth, or Movement.",
            "required_return_shape": "returned_summary, evidence_refs",
            "row_ref": "brick-row:btcr0-p9-05-evidence-integrity",
            "source_facts": [
              "brick/templates/shapes/catalog.yaml",
              "brick/templates/shapes/step-templates.yaml",
              "brick/templates/shapes/chain-presets-brick-protocol.yaml",
              "project/brick-protocol/status/kernel/brick-template-catalog-restructure-0-p8-checker-fire-closure-0601.md"
            ],
            "work_statement": "P9 dogfood observation for evidence-integrity: return local support evidence that this step walked through the split Brick template catalog path."
          },
          {
            "agent_object_ref": "agent-object:inspector",
            "axis": "Agent",
            "row_ref": "btcr0-p9-05-evidence-integrity:agent"
          },
          {
            "axis": "Link",
            "declared_gate_refs": [
              "link-gate:default-transition",
              "link-gate:strict"
            ],
            "movement": "forward",
            "next_brick_instance_ref": "brick-btcr0-p9-closure",
            "row_ref": "btcr0-p9-05-evidence-integrity:link",
            "target_ref": "brick-btcr0-p9-closure"
          }
        ],
        "step_ref": "btcr0-p9-05-evidence-integrity",
        "step_template_ref": "building-step-template:evidence-integrity"
      },
      {
        "rows": [
          {
            "axis": "Brick",
            "brick_instance_ref": "brick-btcr0-p9-06-closure",
            "brick_work_ref": "work:btcr0-p9-06-closure",
            "comparison_rule": "Observe only that required returned fields are present; do not judge success, quality, source truth, or Movement.",
            "required_return_shape": "returned_summary, evidence_refs",
            "row_ref": "brick-row:btcr0-p9-06-closure",
            "source_facts": [
              "brick/templates/shapes/catalog.yaml",
              "brick/templates/shapes/step-templates.yaml",
              "brick/templates/shapes/chain-presets-brick-protocol.yaml",
              "project/brick-protocol/status/kernel/brick-template-catalog-restructure-0-p8-checker-fire-closure-0601.md"
            ],
            "work_statement": "P9 dogfood observation for closure: return local support evidence that this step walked through the split Brick template catalog path."
          },
          {
            "agent_object_ref": "agent-object:coo",
            "axis": "Agent",
            "row_ref": "btcr0-p9-06-closure:agent"
          },
          {
            "axis": "Link",
            "building_lifecycle": {
              "reason": "P9 dogfood closed after split catalog declaration evidence was emitted.",
              "state": "closed"
            },
            "declared_gate_refs": [
              "link-gate:default-transition",
              "link-gate:strict"
            ],
            "movement": "forward",
            "next_brick_instance_ref": "building-boundary:brick-template-catalog-restructure-0-p9-dogfood-closed",
            "row_ref": "btcr0-p9-06-closure:link",
            "target_ref": "building-boundary:brick-template-catalog-restructure-0-p9-dogfood-closed"
          }
        ],
        "step_ref": "btcr0-p9-06-closure",
        "step_template_ref": "building-step-template:closure"
      }
    ],
    "task_source_ref": "project/brick-protocol/status/kernel/brick-template-catalog-restructure-0-p8-checker-fire-closure-0601.md"
  },
  "kind": "declared_building_plan_provenance",
  "not_proven": [
    "declared plan semantic correctness",
    "future Agent or provider behavior"
  ],
  "plan_hash": "a31daa2e4c617ee0fa23a2eaa9d964630f1a955b69a383e991b2139312c7ff9c",
  "plan_hash_algorithm": "sha256",
  "plan_hash_basis": "canonical sorted-key JSON of the pure declared-building-plan copy (runtime walker state excluded)",
  "plan_ref": "building-plan:brick-template-catalog-restructure-0-p9-dogfood",
  "proof_limits": [
    "support declaration provenance evidence only",
    "not source truth",
    "not success judgment",
    "not quality judgment",
    "not Movement authority"
  ]
}
